LICENSE.txt
MANIFEST.in
README.rst
requirements.txt
setup.py
bin/create_lambda_function
bin/test_lambda_function
bin/unpack_example_skills
bin/update_lambda_function
docs/FirstAlexaSkills.rst
docs/Makefile
docs/alexa_skill.png
docs/alexa_skill.svg
docs/conf.py
docs/develop.rst
docs/hackathon_setup.rst
docs/index.rst
docs/installation.rst
docs/make.bat
docs/python_intro.rst
docs/tutorials.rst
docs/_build/html/_static/comment-bright.png
docs/_build/html/_static/comment-close.png
docs/_build/html/_static/comment.png
docs/_build/html/_static/down-pressed.png
docs/_build/html/_static/down.png
docs/_build/html/_static/file.png
docs/_build/html/_static/minus.png
docs/_build/html/_static/plus.png
docs/_build/html/_static/up-pressed.png
docs/_build/html/_static/up.png
src/FirstAlexaSkills/__init__.py
src/FirstAlexaSkills/lambda_utils.py
src/FirstAlexaSkills.egg-info/PKG-INFO
src/FirstAlexaSkills.egg-info/SOURCES.txt
src/FirstAlexaSkills.egg-info/dependency_links.txt
src/FirstAlexaSkills.egg-info/requires.txt
src/FirstAlexaSkills.egg-info/top_level.txt
src/FirstAlexaSkills/data/__init__.py
src/FirstAlexaSkills/data/event_template.json
src/FirstAlexaSkills/data/example_skills.zip