Metadata-Version: 1.1
Name: FirstAlexaSkills
Version: 0.2.0
Summary: A package for learning first steps with Alexa skills
Home-page: https://github.com/means-to-meaning/FirstAlexaSkills
Author: Vlastimil Pis
Author-email: vlasto.pis@gmail.com
License: Amazon Software license
Keywords: alexa skills echo iot aws lambda
Platform: UNKNOWN
Classifier: Development Status :: 3 - Alpha
Classifier: Intended Audience :: Developers
Classifier: Topic :: Education
Classifier: Topic :: Home Automation
Classifier: License :: Other/Proprietary License
Classifier: Programming Language :: Python :: 3
Classifier: Programming Language :: Python :: 3.6
